{
  "1000": [
    { "id": 1001, "Account_Name ": "Teste1000", "E_mail ": "teste1000@teste.com.br" , "Chave ": "1000"}
  ],
  "1001": [
    { "id": 1, "Numero_Contrato": "2001", "Status": 1, "Data_Inicio_Contrato", "01/01/2000"},
    { "id": 2, "Numero_Contrato": "2002", "Status": 1, "Data_Inicio_Contrato", "01/02/2000"},
    { "id": 3, "Numero_Contrato": "2003", "Status": 1, "Data_Inicio_Contrato", "01/03/2000"},
    { "id": 4, "Numero_Contrato": "2004", "Status": 1, "Data_Inicio_Contrato", "01/04/2000"},
    { "id": 5, "Numero_Contrato": "2005", "Status": 1, "Data_Inicio_Contrato", "01/05/2000"},
  ],
  "empresa": {
    "nome": "Teste"
  }
}
